abb_pro33_ardexa.py
abb_pro33_ardexa-0.1.3.dist-info/DESCRIPTION.rst
abb_pro33_ardexa-0.1.3.dist-info/METADATA
abb_pro33_ardexa-0.1.3.dist-info/RECORD
abb_pro33_ardexa-0.1.3.dist-info/WHEEL
abb_pro33_ardexa-0.1.3.dist-info/entry_points.txt
abb_pro33_ardexa-0.1.3.dist-info/metadata.json
abb_pro33_ardexa-0.1.3.dist-info/top_level.txt
