Metadata-Version: 2.0
Name: abb-pro33-ardexa
Version: 0.1.3
Summary: Collect from ABB PRO33 Inverters and send the data to your cloud using Ardexa
Home-page: https://github.com/ardexa/abb-pro33-inverters
Author: Ardexa Pty Limited
Author-email: support@ardexa.com
License: UNKNOWN
Project-URL: Bug Reports, https://github.com/ardexa/abb_pro33-inverters/issues
Project-URL: Source, https://github.com/ardexa/abb_pro33-inverters/
Keywords: abb pro33 solar inverter ardexa
Platform: UNKNOWN
Classifier: License :: OSI Approved :: MIT License
Classifier: Programming Language :: Python :: 2
Classifier: Programming Language :: Python :: 2.7
Classifier: Programming Language :: Python :: 3
Classifier: Programming Language :: Python :: 3.4
Classifier: Programming Language :: Python :: 3.5
Classifier: Programming Language :: Python :: 3.6
Requires-Python: >=2.7
Requires-Dist: future
Requires-Dist: ardexaplugin
Requires-Dist: Click
